go_over/__init__.py
go_over/__main__.py
go_over/__setup_gr.py
go_over/example_module.py
go_over/goodreads/__init__.py
go_over/goodreads/book.py
go_over/goodreads/bookread.py
go_over/goodreads/bookshelf.py
go_over/goodreads/bookshelfComplement.py
go_over/goodreads/generator.py
go_over/goodreads/loader.py
go_over/goodreads/printer.py
go_over/goodreads/processor.py
go_over-0.4.3.dist-info/LICENCE
go_over-0.4.3.dist-info/METADATA
go_over-0.4.3.dist-info/WHEEL
go_over-0.4.3.dist-info/entry_points.txt
go_over-0.4.3.dist-info/top_level.txt
go_over-0.4.3.dist-info/RECORD
