Metadata-Version: 2.1
Name: go-over
Version: 0.4.3
Summary: Converts Goodreads CSV files to custom desing JSON for jekyll blog consumption.
Home-page: https://github.com/josealobato/go-over
Author: Jose A. Lobato
Author-email: jose.lobato@me.com
Project-URL: Bug Tracker, https://github.com/josealobato/go-over/issues
Classifier: Programming Language :: Python :: 3
Classifier: License :: OSI Approved :: MIT License
Classifier: Operating System :: OS Independent
Requires-Python: >=3.6
License-File: LICENCE
